freeproxy/__init__.py
freeproxy/freeproxy.py
freeproxy/modules/__init__.py
freeproxy/modules/proxies/__init__.py
freeproxy/modules/proxies/base.py
freeproxy/modules/proxies/databay.py
freeproxy/modules/proxies/fineproxy.py
freeproxy/modules/proxies/freeproxydb.py
freeproxy/modules/proxies/freeproxylist.py
freeproxy/modules/proxies/geonode.py
freeproxy/modules/proxies/ihuan.py
freeproxy/modules/proxies/ip3366.py
freeproxy/modules/proxies/ip89.py
freeproxy/modules/proxies/iplocate.py
freeproxy/modules/proxies/jiliuip.py
freeproxy/modules/proxies/kuaidaili.py
freeproxy/modules/proxies/kxdaili.py
freeproxy/modules/proxies/proxifly.py
freeproxy/modules/proxies/proxydaily.py
freeproxy/modules/proxies/proxydb.py
freeproxy/modules/proxies/proxyelite.py
freeproxy/modules/proxies/proxyhub.py
freeproxy/modules/proxies/proxylist.py
freeproxy/modules/proxies/proxyscrape.py
freeproxy/modules/proxies/qiyunip.py
freeproxy/modules/proxies/spysone.py
freeproxy/modules/proxies/thespeedx.py
freeproxy/modules/proxies/tomcat1235.py
freeproxy/modules/utils/__init__.py
freeproxy/modules/utils/chromium.py
freeproxy/modules/utils/data.py
freeproxy/modules/utils/io.py
freeproxy/modules/utils/iplocation.py
freeproxy/modules/utils/logger.py
freeproxy/modules/utils/modulebuilder.py
freeproxy/modules/utils/proxychecker.py
pyfreeproxy-0.3.4.dist-info/LICENSE
pyfreeproxy-0.3.4.dist-info/METADATA
pyfreeproxy-0.3.4.dist-info/WHEEL
pyfreeproxy-0.3.4.dist-info/top_level.txt
pyfreeproxy-0.3.4.dist-info/zip-safe
pyfreeproxy-0.3.4.dist-info/RECORD
