Metadata-Version: 2.1
Name: pyfreeproxy
Version: 0.3.4
Summary: FreeProxy: Collecting free proxies from internet.
Home-page: https://github.com/CharlesPikachu/freeproxy
Author: Zhenchao Jin
Author-email: charlesblwx@gmail.com
License: Apache License 2.0
Classifier: License :: OSI Approved :: Apache Software License
Classifier: Programming Language :: Python :: 3
Classifier: Intended Audience :: Developers
Classifier: Operating System :: OS Independent
License-File: LICENSE
Requires-Dist: requests
Requires-Dist: beautifulsoup4
Requires-Dist: fake-useragent
Requires-Dist: prettytable
Requires-Dist: lxml
Requires-Dist: platformdirs
Requires-Dist: playwright
Requires-Dist: json-repair
Requires-Dist: tqdm
